histomicstk/__init__.py
histomicstk/cli/__main__.py
histomicstk/cli/slicer_cli_list.json
histomicstk/cli/docker-entrypoint.sh
histomicstk/cli/__init__.py
histomicstk/cli/utils.py
histomicstk/cli/dask_config.yaml
histomicstk/cli/ColorDeconvolution/ColorDeconvolution.py
histomicstk/cli/ColorDeconvolution/ColorDeconvolution.xml
histomicstk/cli/ColorDeconvolution/__init__.py
histomicstk/cli/SuperpixelSegmentation/SuperpixelSegmentation.py
histomicstk/cli/SuperpixelSegmentation/SuperpixelSegmentation.xml
histomicstk/cli/SuperpixelSegmentation/__init__.py
histomicstk/cli/SeparateStainsMacenkoPCA/SeparateStainsMacenkoPCA.xml
histomicstk/cli/SeparateStainsMacenkoPCA/SeparateStainsMacenkoPCA.py
histomicstk/cli/SeparateStainsMacenkoPCA/__init__.py
histomicstk/cli/BackgroundIntensity/BackgroundIntensity.xml
histomicstk/cli/BackgroundIntensity/BackgroundIntensity.py
histomicstk/cli/BackgroundIntensity/__init__.py
histomicstk/cli/NucleiClassification/NucleiClassification.py
histomicstk/cli/NucleiClassification/NucleiClassification.xml
histomicstk/cli/NucleiClassification/__init__.py
histomicstk/cli/ComputeNucleiFeatures/ComputeNucleiFeatures.xml
histomicstk/cli/ComputeNucleiFeatures/ComputeNucleiFeatures.py
histomicstk/cli/ComputeNucleiFeatures/__init__.py
histomicstk/cli/ComputeNucleiFeatures/README.md
histomicstk/cli/NucleiDetection/NucleiDetection.xml
histomicstk/cli/NucleiDetection/__init__.py
histomicstk/cli/NucleiDetection/NucleiDetection.py
histomicstk/cli/PositivePixelCount/PositivePixelCount.xml
histomicstk/cli/PositivePixelCount/PositivePixelCount.py
histomicstk/cli/PositivePixelCount/__init__.py
histomicstk/cli/SeparateStainsXuSnmf/SeparateStainsXuSnmf.xml
histomicstk/cli/SeparateStainsXuSnmf/__init__.py
histomicstk/cli/SeparateStainsXuSnmf/SeparateStainsXuSnmf.py
histomicstk/features/graycomatrixext.py
histomicstk/features/compute_gradient_features.py
histomicstk/features/compute_morphometry_features.py
histomicstk-1.4.0.dist-info/NOTICE
histomicstk-1.4.0.dist-info/LICENSE
histomicstk-1.4.0.dist-info/WHEEL
histomicstk-1.4.0.dist-info/AUTHORS.rst
histomicstk-1.4.0.dist-info/RECORD
histomicstk-1.4.0.dist-info/top_level.txt
histomicstk-1.4.0.dist-info/entry_points.txt
histomicstk-1.4.0.dist-info/METADATA
