Metadata-Version: 2.2
Name: histomicstk
Version: 1.4.0
Summary: A Python toolkit for Histopathology Image Analysis
Home-page: https://github.com/DigitalSlideArchive/HistomicsTK
Author: Kitware, Inc.
Author-email: developers@digitalslidearchive.net
License: Apache Software License 2.0
Keywords: histomicstk
Classifier: Development Status :: 5 - Production/Stable
Classifier: License :: OSI Approved :: Apache Software License
Classifier: Programming Language :: Python :: 3
Classifier: Programming Language :: Python :: 3.9
Classifier: Programming Language :: Python :: 3.10
Classifier: Programming Language :: Python :: 3.11
Classifier: Programming Language :: Python :: 3.12
Classifier: Topic :: Scientific/Engineering :: Artificial Intelligence
Classifier: Topic :: Software Development :: Libraries :: Python Modules
Requires-Python: >=3.9
License-File: LICENSE
License-File: NOTICE
License-File: AUTHORS.rst
Requires-Dist: girder-client
Requires-Dist: nimfa
Requires-Dist: numpy
Requires-Dist: scipy
Requires-Dist: Pillow
Requires-Dist: pandas
Requires-Dist: scikit-image
Requires-Dist: scikit-learn
Requires-Dist: imageio
Requires-Dist: shapely
Requires-Dist: sqlalchemy
Requires-Dist: matplotlib
Requires-Dist: pyvips
Requires-Dist: dask[dataframe]<2024.11.0
Requires-Dist: distributed
Requires-Dist: large-image[sources]; sys_platform == "linux" or sys_platform == "linux2"
Requires-Dist: large-image[common]; sys_platform != "linux" and sys_platform != "linux2"
Requires-Dist: large-image-converter; sys_platform == "linux" or sys_platform == "linux2"
Requires-Dist: girder-slicer-cli-web
Requires-Dist: ctk-cli
Requires-Dist: opencv-python-headless
Dynamic: author
Dynamic: author-email
Dynamic: classifier
Dynamic: description
Dynamic: description-content-type
Dynamic: home-page
Dynamic: keywords
Dynamic: license
Dynamic: requires-dist
Dynamic: requires-python
Dynamic: summary
